pytest_lf_skip/__init__.py
pytest_lf_skip/constants.py
pytest_lf_skip/hooks.py
pytest_lf_skip/lf_skip.py
pytest_lf_skip/plugin.py
pytest_lf_skip/py.typed
pytest_lf_skip-1.1.0.dist-info/METADATA
pytest_lf_skip-1.1.0.dist-info/WHEEL
pytest_lf_skip-1.1.0.dist-info/entry_points.txt
pytest_lf_skip-1.1.0.dist-info/RECORD
