Metadata-Version: 2.4
Name: pytest-lf-skip
Version: 1.1.0
Summary: A pytest plugin which makes `--last-failed` skip instead of deselect tests.
Project-URL: Changelog, https://github.com/alexfayers/pytest-lf-skip/blob/main/CHANGELOG.md
Project-URL: Homepage, https://github.com/alexfayers/pytest-lf-skip
Project-URL: Source, https://github.com/alexfayers/pytest-lf-skip
Author-email: Alex Fayers <alex@fayers.com>
Classifier: Development Status :: 4 - Beta
Classifier: Framework :: Pytest
Classifier: Intended Audience :: Developers
Classifier: Operating System :: MacOS
Classifier: Operating System :: Microsoft :: Windows
Classifier: Operating System :: POSIX
Classifier: Operating System :: Unix
Classifier: Programming Language :: Python :: 3 :: Only
Classifier: Programming Language :: Python :: 3.10
Classifier: Programming Language :: Python :: 3.11
Classifier: Programming Language :: Python :: 3.12
Classifier: Programming Language :: Python :: 3.13
Classifier: Topic :: Software Development :: Testing
Classifier: Topic :: Utilities
Classifier: Typing :: Typed
Requires-Python: >=3.10
Requires-Dist: pytest>=8.3.5
